Classfile /E:/JavaWeb/test/src/test/Point.class
  Last modified 2017-6-3; size 524 bytes
  MD5 checksum 266bd003a32e2dd08614e07476c93dd4
  Compiled from "Point.java"
public class test.Point
  SourceFile: "Point.java"
  minor version: 0
  major version: 52
  flags: ACC_PUBLIC, ACC_SUPER
Constant pool:
   #1 = Methodref          #11.#25        //  java/lang/Object."<init>":()V
   #2 = Fieldref           #4.#26         //  test/Point.x:D
   #3 = Fieldref           #4.#27         //  test/Point.y:D
   #4 = Class              #28            //  test/Point
   #5 = Methodref          #4.#29         //  test/Point."<init>":(DD)V
   #6 = Double             3.0d
   #8 = Double             4.0d
  #10 = Methodref          #4.#30         //  test/Point.distance:(Ltest/Point;)D
  #11 = Class              #31            //  java/lang/Object
  #12 = Utf8               x
  #13 = Utf8               D
  #14 = Utf8               y
  #15 = Utf8               <init>
  #16 = Utf8               (DD)V
  #17 = Utf8               Code
  #18 = Utf8               LineNumberTable
  #19 = Utf8               distance
  #20 = Utf8               (Ltest/Point;)D
  #21 = Utf8               main
  #22 = Utf8               ([Ljava/lang/String;)V
  #23 = Utf8               SourceFile
  #24 = Utf8               Point.java
  #25 = NameAndType        #15:#32        //  "<init>":()V
  #26 = NameAndType        #12:#13        //  x:D
  #27 = NameAndType        #14:#13        //  y:D
  #28 = Utf8               test/Point
  #29 = NameAndType        #15:#16        //  "<init>":(DD)V
  #30 = NameAndType        #19:#20        //  distance:(Ltest/Point;)D
  #31 = Utf8               java/lang/Object
  #32 = Utf8               ()V
{
  public test.Point(double, double);
    descriptor: (DD)V
    flags: ACC_PUBLIC
    Code:
      stack=3, locals=5, args_size=3
         0: aload_0       
         1: invokespecial #1                  // Method java/lang/Object."<init>":()V
         4: aload_0       
         5: dload_1       
         6: putfield      #2                  // Field x:D
         9: aload_0       
        10: dload_3       
        11: putfield      #3                  // Field y:D
        14: return        
      LineNumberTable:
        line 8: 0
        line 9: 4
        line 10: 9
        line 11: 14

  public static void main(java.lang.String[]);
    descriptor: ([Ljava/lang/String;)V
    flags: ACC_PUBLIC, ACC_STATIC
    Code:
      stack=6, locals=5, args_size=1
         0: new           #4                  // class test/Point
         3: dup           
         4: dconst_0      
         5: dconst_0      
         6: invokespecial #5                  // Method "<init>":(DD)V
         9: astore_1      
        10: new           #4                  // class test/Point
        13: dup           
        14: ldc2_w        #6                  // double 3.0d
        17: ldc2_w        #8                  // double 4.0d
        20: invokespecial #5                  // Method "<init>":(DD)V
        23: astore_2      
        24: aload_1       
        25: aload_2       
        26: invokespecial #10                 // Method distance:(Ltest/Point;)D
        29: dstore_3      
        30: return        
      LineNumberTable:
        line 23: 0
        line 24: 10
        line 26: 24
        line 27: 30
}
