Classfile /E:/JavaWeb/test/src/test/TestInheritance.class
  Last modified 2017-6-6; size 438 bytes
  MD5 checksum a6cbd70a0a37ec4c8a5762c0599c7933
  Compiled from "TestInheritance.java"
class test.TestInheritance
  SourceFile: "TestInheritance.java"
  minor version: 0
  major version: 52
  flags: ACC_SUPER
Constant pool:
   #1 = Methodref          #9.#18         //  java/lang/Object."<init>":()V
   #2 = Class              #19            //  test/Child
   #3 = Methodref          #2.#18         //  test/Child."<init>":()V
   #4 = Methodref          #2.#20         //  test/Child.setZ1:(I)V
   #5 = Fieldref           #2.#21         //  test/Child.x1:I
   #6 = Fieldref           #2.#22         //  test/Child.y1:I
   #7 = Methodref          #2.#23         //  test/Child.doSomething:()I
   #8 = Class              #24            //  test/TestInheritance
   #9 = Class              #25            //  java/lang/Object
  #10 = Utf8               <init>
  #11 = Utf8               ()V
  #12 = Utf8               Code
  #13 = Utf8               LineNumberTable
  #14 = Utf8               main
  #15 = Utf8               ([Ljava/lang/String;)V
  #16 = Utf8               SourceFile
  #17 = Utf8               TestInheritance.java
  #18 = NameAndType        #10:#11        //  "<init>":()V
  #19 = Utf8               test/Child
  #20 = NameAndType        #26:#27        //  setZ1:(I)V
  #21 = NameAndType        #28:#29        //  x1:I
  #22 = NameAndType        #30:#29        //  y1:I
  #23 = NameAndType        #31:#32        //  doSomething:()I
  #24 = Utf8               test/TestInheritance
  #25 = Utf8               java/lang/Object
  #26 = Utf8               setZ1
  #27 = Utf8               (I)V
  #28 = Utf8               x1
  #29 = Utf8               I
  #30 = Utf8               y1
  #31 = Utf8               doSomething
  #32 = Utf8               ()I
{
  test.TestInheritance();
    descriptor: ()V
    flags: 
    Code:
      stack=1, locals=1, args_size=1
         0: aload_0       
         1: invokespecial #1                  // Method java/lang/Object."<init>":()V
         4: return        
      LineNumberTable:
        line 3: 0

  public static void main(java.lang.String[]);
    descriptor: ([Ljava/lang/String;)V
    flags: ACC_PUBLIC, ACC_STATIC
    Code:
      stack=2, locals=3, args_size=1
         0: new           #2                  // class test/Child
         3: dup           
         4: invokespecial #3                  // Method test/Child."<init>":()V
         7: astore_1      
         8: aload_1       
         9: iconst_3      
        10: invokevirtual #4                  // Method test/Child.setZ1:(I)V
        13: aload_1       
        14: iconst_1      
        15: putfield      #5                  // Field test/Child.x1:I
        18: aload_1       
        19: iconst_2      
        20: putfield      #6                  // Field test/Child.y1:I
        23: aload_1       
        24: invokevirtual #7                  // Method test/Child.doSomething:()I
        27: istore_2      
        28: return        
      LineNumberTable:
        line 7: 0
        line 9: 8
        line 10: 13
        line 11: 18
        line 13: 23
        line 14: 28
}
